MANIFEST.in
README.rst
setup.cfg
setup.py
samlauth/__init__.py
samlauth/bootstrap.py
samlauth/helpers.py
samlauth/controllers/__init__.py
samlauth/controllers/root.py
samlauth/lib/__init__.py
samlauth/public/__init__.py
samlauth/templates/__init__.py
tgapp_samlauth.egg-info/PKG-INFO
tgapp_samlauth.egg-info/SOURCES.txt
tgapp_samlauth.egg-info/dependency_links.txt
tgapp_samlauth.egg-info/entry_points.txt
tgapp_samlauth.egg-info/not-zip-safe
tgapp_samlauth.egg-info/requires.txt
tgapp_samlauth.egg-info/top_level.txt