Metadata-Version: 1.0
Name: tgapp-samlauth
Version: 0.0.2
Summary: Pluggable application for TurboGears2 to authenticate users against an SAML2 Identity Provider
Home-page: https://bitbucket.org/axant/tgapp-samlauth
Author: AXANT
Author-email: tech@axant.it
License: UNKNOWN
Keywords: turbogears2.application
Platform: UNKNOWN
